resplendent/__init__.py
resplendent/__main__.py
resplendent/util.py
resplendent/version.py
resplendent/filters/__init__.py
resplendent/filters/filterdump.py
resplendent/filters/restructuredtext.py
resplendent-0.3.5.dist-info/LICENSE
resplendent-0.3.5.dist-info/METADATA
resplendent-0.3.5.dist-info/WHEEL
resplendent-0.3.5.dist-info/top_level.txt
resplendent-0.3.5.dist-info/RECORD
